pody/__init__.py
pody/api/__init__.py
pody/cli/client.py
pody/cli/client_x.py
pody/cli/log.py
pody/cli/serve.py
pody/cli/user.py
pody/cli/util.py
pody/config.default.toml
pody/config.py
pody/doc/.gitkeep
pody/eng/__init__.py
pody/eng/db.py
pody/eng/docker.py
pody/eng/errors.py
pody/eng/gpu.py
pody/eng/log.py
pody/eng/nparse.py
pody/eng/resmon.py
pody/eng/user.py
pody/eng/utils.py
pody/svc/app.py
pody/svc/app_base.py
pody/svc/daemon.py
pody/svc/router_host.py
pody/svc/router_image.py
pody/svc/router_pod.py
pody/svc/router_stat.py
pody/svc/router_user.py
pody/version.py
pody-0.3.4.dist-info/METADATA
pody-0.3.4.dist-info/WHEEL
pody-0.3.4.dist-info/entry_points.txt
pody-0.3.4.dist-info/RECORD
