Metadata-Version: 2.3
Name: pody
Version: 0.3.4
Summary: Pod manager for docker, give limited access to docker for clients.
Author: Li, Mengxun
Author-email: mengxunli@whu.edu.cn
Requires-Python: >=3.10
Classifier: Programming Language :: Python :: 3
Classifier: Programming Language :: Python :: 3.10
Classifier: Programming Language :: Python :: 3.11
Classifier: Programming Language :: Python :: 3.12
Classifier: Programming Language :: Python :: 3.13
Provides-Extra: server
Requires-Dist: docker ; extra == "server"
Requires-Dist: fastapi (==0.*) ; extra == "server"
Requires-Dist: nvidia-ml-py ; extra == "server"
Requires-Dist: psutil ; extra == "server"
Requires-Dist: requests
Requires-Dist: rich
Requires-Dist: toml ; extra == "server"
Requires-Dist: typer (==0.*)
Requires-Dist: uvicorn (==0.*) ; extra == "server"
